{
    "version": "0.42.1",
    "architecture": {
        "32bit": {
            "url": "https://github.com/secrethub/secrethub-cli/releases/download/v0.42.1/secrethub-v0.42.1-windows-386.zip",
            "bin": [
                "bin/secrethub.exe"
            ],
            "hash": "ab1cbc4f0df59d1dd236f4c4db5418afe9fe9091d0b551da6ef7a9d1a1a0d4f7"
        },
        "64bit": {
            "url": "https://github.com/secrethub/secrethub-cli/releases/download/v0.42.1/secrethub-v0.42.1-windows-amd64.zip",
            "bin": [
                "bin/secrethub.exe"
            ],
            "hash": "a5c81f96d18edb30e1a6c846c13a507e845e5043ad57846b22127062fc881fdd"
        }
    },
    "homepage": "https://secrethub.io",
    "license": "Apache-2.0",
    "description": "Command-line interface for SecretHub"
}